csvtogitissue/__init__.py
csvtogitissue/csvtogitissue.py
csvtogitissue-1.0.4.dist-info/METADATA
csvtogitissue-1.0.4.dist-info/RECORD
csvtogitissue-1.0.4.dist-info/WHEEL
csvtogitissue-1.0.4.dist-info/top_level.txt
