Metadata-Version: 2.1
Name: csvtogitissue
Version: 1.0.4
Summary: A simple package to help convert CSV file entries to GITHub issues via API v3 (Private and Public repositories)
Home-page: https://github.com/sanjeven/CSV-to-GIThub-issue-creator
Author: Sanjeven Ramakrishnan
Author-email: sanjeven@gmail.com
License: UNKNOWN
Platform: UNKNOWN
Classifier: Programming Language :: Python :: 3
Classifier: License :: OSI Approved :: MIT License
Classifier: Operating System :: OS Independent
